Metadata-Version: 1.1
Name: aetf
Version: 0.0.4
Summary: Python package for autoencoding(Deep Learning) functionality using TensorFlow
Home-page: https://bitbucket.org/HNGML/aetf
Author: hngml
Author-email: nilesh.chaudhari@healthnextgen.com
License: MIT
Platform: UNKNOWN
Classifier: Development Status :: 1 - Planning
Classifier: License :: OSI Approved :: MIT License
Classifier: Programming Language :: Python :: 2.7
Classifier: Topic :: Software Development :: Libraries :: Python Modules
